setup.py
stepboard/__init__.py
stepboard/applications.py
stepboard/channels.py
stepboard/config.py
stepboard/guilds.py
stepboard/message.py
stepboard/roles.py
stepboard/threads.py
stepboard/user.py
stepboard/webhooks.py
stepboard.egg-info/PKG-INFO
stepboard.egg-info/SOURCES.txt
stepboard.egg-info/dependency_links.txt
stepboard.egg-info/top_level.txt