Metadata-Version: 2.1
Name: stepboard
Version: 1.1.0
Summary: A simple library for making a dashboard in a flask/django.
Home-page: UNKNOWN
Author: Stępującybrat#1017
Author-email: maciejwisniewski.ja@gmail.com
License: MIT
Platform: UNKNOWN
